airfold/__init__.py
airfold/config.py
airfold/context.py
airfold/format.py
airfold/log.py
airfold/models.py
airfold/parse.py
airfold/type.py
airfold/utils.py
airfold/cli/__init__.py
airfold/cli/cli.py
airfold/cli/pipe.py
airfold/runtime/__init__.py
airfold/runtime/ch.py
airfold/runtime/ch_cluster.py
airfold/runtime/runtime.py
airfold/runtime/type.py
airfold/storage/__init__.py
airfold/storage/ch.py
airfold/storage/sqlite.py
airfold/storage/storage.py
airfold/storage/type.py
airfold-0.2.0.dist-info/LICENSE
airfold-0.2.0.dist-info/METADATA
airfold-0.2.0.dist-info/WHEEL
airfold-0.2.0.dist-info/entry_points.txt
airfold-0.2.0.dist-info/top_level.txt
airfold-0.2.0.dist-info/RECORD
