Metadata-Version: 2.1
Name: airfold
Version: 0.2.0
Summary: Pioneering real-time data
Author-email: Julian Gilyadov <israelg99@gmail.com>, Constantine Peresypkin <pconstantine@gmail.com>
License: Apache-2.0
Requires-Python: <4,>=3.10
License-File: LICENSE
Requires-Dist: clickhouse-connect (>=0.5.25)
Requires-Dist: clickhouse-driver
Requires-Dist: kafka-python
Requires-Dist: pydantic (>=1.10.4)
Requires-Dist: pyyaml
Requires-Dist: rich
Requires-Dist: sqlglot (>=15.0.0)
Requires-Dist: typer
Provides-Extra: test
Requires-Dist: bandit ; extra == 'test'
Requires-Dist: black ; extra == 'test'
Requires-Dist: coverage ; extra == 'test'
Requires-Dist: ipykernel ; extra == 'test'
Requires-Dist: ipython ; extra == 'test'
Requires-Dist: jupyter ; extra == 'test'
Requires-Dist: mkdocs-material ; extra == 'test'
Requires-Dist: mkdocstrings[python] ; extra == 'test'
Requires-Dist: mypy ; extra == 'test'
Requires-Dist: numpy ; extra == 'test'
Requires-Dist: pandas ; extra == 'test'
Requires-Dist: pytest ; extra == 'test'
Requires-Dist: pytest-docker-compose ; extra == 'test'
Requires-Dist: pytest-dotenv ; extra == 'test'
Requires-Dist: retry ; extra == 'test'
Requires-Dist: types-pyyaml ; extra == 'test'
Requires-Dist: types-retry ; extra == 'test'
